marshmallow_geojson/__init__.py
marshmallow_geojson/_base.py
marshmallow_geojson/feature.py
marshmallow_geojson/feature_collection.py
marshmallow_geojson/geojson.py
marshmallow_geojson/geometry.py
marshmallow_geojson/geometry_collection.py
marshmallow_geojson/line_string.py
marshmallow_geojson/multi_line_string.py
marshmallow_geojson/multi_point.py
marshmallow_geojson/multi_polygon.py
marshmallow_geojson/object_type.py
marshmallow_geojson/point.py
marshmallow_geojson/polygon.py
marshmallow_geojson/property.py
marshmallow_geojson/validate.py
marshmallow_geojson-0.6.1.dist-info/METADATA
marshmallow_geojson-0.6.1.dist-info/WHEEL
marshmallow_geojson-0.6.1.dist-info/licenses/AUTHORS
marshmallow_geojson-0.6.1.dist-info/licenses/LICENSE
marshmallow_geojson-0.6.1.dist-info/RECORD
