Metadata-Version: 2.4
Name: marshmallow_geojson
Version: 0.6.1
Summary: Marshmallow schema validation for GeoJson
License: MIT
License-File: AUTHORS
License-File: LICENSE
Keywords: marshmallow,validation,geojson,schema,gis,geo,json,json-schema,rest,swagger,openapi
Author: Aliaksandr Vaskevich
Author-email: vaskevic.an@gmail.com
Requires-Python: >=3.9,<4.0
Classifier: Intended Audience :: Developers
Classifier: License :: OSI Approved :: MIT License
Classifier: Programming Language :: Python :: 3
Classifier: Programming Language :: Python :: 3.9
Classifier: Programming Language :: Python :: 3.10
Classifier: Programming Language :: Python :: 3.11
Classifier: Programming Language :: Python :: 3.12
Classifier: Programming Language :: Python :: 3.13
Classifier: Programming Language :: Python :: 3.14
Classifier: Programming Language :: Python :: Implementation :: CPython
Classifier: Topic :: Scientific/Engineering :: GIS
Requires-Dist: marshmallow (>=3.8,<5.0)
Project-URL: Documentation, https://github.com/folt/marshmallow-geojson
Project-URL: Homepage, https://github.com/folt/marshmallow-geojson
Project-URL: Repository, https://github.com/folt/marshmallow-geojson
